{
  "environment":      "prod",
  "azure": {
    "subscription_id": "<SUBSCRIPTION_ID>",
    "tenant_id":        "<TENANT_ID>",
    "location":         "eastus"
  },
  "naming": {
    "project_prefix":     "fpp",
    "resource_group":     "rg-fpp-prod",
    "automation_account": "aa-fpp-prod",
    "key_vault":          "kv-fpp-prod",
    "log_analytics":      "law-fpp-prod",
    "fabric_capacity":    "fabric-fpp-prod"
  },
  "auth": {
    "mode": "service_principal",
    "client_id":             "<SP_CLIENT_ID_PROD>",
    "client_secret_kv_name": "sp-client-secret"
  },
  "fabric": {
    "sku": "F4",
    "admin_email": "admin@yourdomain.com"
  },
  "tags": {
    "project":     "fabric-plug-and-play",
    "environment": "prod",
    "cost_center": "engineering",
    "managed_by":  "bicep"
  }
}
